azx/__init__.py
azx/agents.py
azx/arguments.py
azx/configure.py
azx/prompt.py
azx/renderer.py
azx/storage.py
azx/tools.py
azx-0.1.9.dist-info/METADATA
azx-0.1.9.dist-info/WHEEL
azx-0.1.9.dist-info/entry_points.txt
azx-0.1.9.dist-info/top_level.txt
azx-0.1.9.dist-info/RECORD
