Metadata-Version: 2.4
Name: azx
Version: 0.1.9
Summary: Add your description here
Requires-Python: >=3.11
Requires-Dist: fastmcp>=2.12.0
Requires-Dist: markdown-it-py>=3.0.0
Requires-Dist: markitdown>=0.1.2
Requires-Dist: openai>=1.99.6
Requires-Dist: prompt-toolkit>=3.0.51
Requires-Dist: pyyaml>=6.0.2
Requires-Dist: requests>=2.32.5
Requires-Dist: rich>=14.1.0
Requires-Dist: socksio>=1.0.0
